pydobotplus/__init__.py
pydobotplus/dobotplus.py
pydobotplus/message.py
pydobotplus-0.1.1.dist-info/LICENSE.txt
pydobotplus-0.1.1.dist-info/METADATA
pydobotplus-0.1.1.dist-info/WHEEL
pydobotplus-0.1.1.dist-info/top_level.txt
pydobotplus-0.1.1.dist-info/RECORD
