Metadata-Version: 2.1
Name: pydobotplus
Version: 0.1.1
Summary: Python library for Dobot Magician upgraded
Home-page: https://github.com/sammydick22/pydobotplus
Author: sammydick22
Author-email: sjeother@gmail.com
Keywords: dobot,magician,robotics,m1
License-File: LICENSE.txt
Requires-Dist: pyserial ==3.4
